{
  "version": "2.0-modular",
  "type": "cryptoTree-trunk",
  "fields": [
    {
      "id": "ma-investment-banking",
      "file": "branches/investmentBanking.json"
    },
    {
      "id": "PE",
      "file": "branches/PEbranch.json"
    },
    {
      "id": "VC",
      "file": "branches/VCbranch.json"
    },
    {
      "id": "Quant",
      "file": "branches/QuantBranch.json"
    },
    {
      "id": "PubFin",
      "file": "branches/pubfinBranch.json"
    },
    {
      "id": "hedge-funds-root",
      "file": "branches/HedgeFbranche.json"
    },
    {
      "id": "risk-management-sector",
      "file": "branches/RiskMbranche.json"
    },
    {
      "id": "asset-management-root",
      "file": "branches/AssetMangementBranch.json"
    },
    {
      "id": "fpna-root",
      "file": "branches/FPnAbranch.json"
    }
  ]
}
